mat3ra/__init__.py
mat3ra/wode/__init__.py
mat3ra/wode/context/__init__.py
mat3ra/wode/context/providers/__init__.py
mat3ra/wode/context/providers/points_grid_data_provider.py
mat3ra/wode/context/providers/by_application/__init__.py
mat3ra/wode/context/providers/by_application/executable_context_provider.py
mat3ra/wode/context/providers/by_application/espresso/__init__.py
mat3ra/wode/context/providers/by_application/espresso/qe_pwx_context_provider.py
mat3ra/wode/mixins/__init__.py
mat3ra/wode/mixins/flowchart_units_manager.py
mat3ra/wode/subworkflows/__init__.py
mat3ra/wode/subworkflows/subworkflow.py
mat3ra/wode/units/__init__.py
mat3ra/wode/units/execution.py
mat3ra/wode/units/subworkflow.py
mat3ra/wode/units/unit.py
mat3ra/wode/workflows/__init__.py
mat3ra/wode/workflows/workflow.py
mat3ra_wode-2026.1.13.post0.dist-info/licenses/LICENSE.md
mat3ra_wode-2026.1.13.post0.dist-info/METADATA
mat3ra_wode-2026.1.13.post0.dist-info/WHEEL
mat3ra_wode-2026.1.13.post0.dist-info/top_level.txt
mat3ra_wode-2026.1.13.post0.dist-info/RECORD
