Metadata-Version: 2.4
Name: mat3ra-wode
Version: 2026.1.13.post0
Summary: WOrkflow DEfinitions
Author-email: "Exabyte Inc." <info@mat3ra.com>
License: # LICENSE
Classifier: Programming Language :: Python
Classifier: Programming Language :: Python :: 3
Classifier: Programming Language :: Python :: 3.10
Classifier: Programming Language :: Python :: 3.11
Classifier: Programming Language :: Python :: 3.12
Classifier: Programming Language :: Python :: 3.13
Classifier: Development Status :: 3 - Alpha
Classifier: Topic :: Software Development
Requires-Python: >=3.10
License-File: LICENSE.md
Requires-Dist: numpy
Requires-Dist: mat3ra-utils
Requires-Dist: mat3ra-esse
Requires-Dist: mat3ra-mode
Requires-Dist: mat3ra-ade
Requires-Dist: mat3ra-code
Requires-Dist: mat3ra-standata
Provides-Extra: dev
Requires-Dist: pre-commit; extra == "dev"
Requires-Dist: black; extra == "dev"
Requires-Dist: ruff; extra == "dev"
Requires-Dist: isort; extra == "dev"
Requires-Dist: mypy; extra == "dev"
Requires-Dist: pip-tools; extra == "dev"
Provides-Extra: tests
Requires-Dist: coverage[toml]>=5.3; extra == "tests"
Requires-Dist: pytest; extra == "tests"
Requires-Dist: pytest-cov; extra == "tests"
Provides-Extra: all
Requires-Dist: mat3ra-wode[tests]; extra == "all"
Requires-Dist: mat3ra-wode[dev]; extra == "all"
Dynamic: license-file
